<annotation>
	<folder>personball</folder>
	<filename>471c5cd4e06b4d3cbc11a5fcda0c4254.jpeg</filename>
	<path>/Users/gaocheng/Desktop/ML/202111251600/personball/471c5cd4e06b4d3cbc11a5fcda0c4254.jpeg</path>
	<source>
		<database>Unknown</database>
	</source>
	<size>
		<width>3072</width>
		<height>2040</height>
		<depth>3</depth>
	</size>
	<segmented>0</segmented>
	<object>
		<name>ball</name>
		<pose>Unspecified</pose>
		<truncated>0</truncated>
		<difficult>0</difficult>
		<bndbox>
			<xmin>1443</xmin>
			<ymin>700</ymin>
			<xmax>1849</xmax>
			<ymax>1112</ymax>
		</bndbox>
	</object>
	<object>
		<name>ball</name>
		<pose>Unspecified</pose>
		<truncated>0</truncated>
		<difficult>0</difficult>
		<bndbox>
			<xmin>2361</xmin>
			<ymin>746</ymin>
			<xmax>2719</xmax>
			<ymax>1118</ymax>
		</bndbox>
	</object>
</annotation>
