<annotation>
	<folder>round</folder>
	<filename>56b8795fc8381577bdc2a6d9ef053f62.jpeg</filename>
	<path>/Users/gaocheng/Desktop/ML/round/56b8795fc8381577bdc2a6d9ef053f62.jpeg</path>
	<source>
		<database>Unknown</database>
	</source>
	<size>
		<width>1216</width>
		<height>856</height>
		<depth>3</depth>
	</size>
	<segmented>0</segmented>
	<object>
		<name>ball</name>
		<pose>Unspecified</pose>
		<truncated>0</truncated>
		<difficult>0</difficult>
		<bndbox>
			<xmin>616</xmin>
			<ymin>461</ymin>
			<xmax>715</xmax>
			<ymax>563</ymax>
		</bndbox>
	</object>
</annotation>
