<annotation>
	<folder>tb</folder>
	<filename>aa8f608c14865b9ebcd3dd93064169d8.jpeg</filename>
	<path>/Users/gaocheng/Desktop/ML/tb/aa8f608c14865b9ebcd3dd93064169d8.jpeg</path>
	<source>
		<database>Unknown</database>
	</source>
	<size>
		<width>1080</width>
		<height>608</height>
		<depth>3</depth>
	</size>
	<segmented>0</segmented>
	<object>
		<name>ball</name>
		<pose>Unspecified</pose>
		<truncated>0</truncated>
		<difficult>0</difficult>
		<bndbox>
			<xmin>360</xmin>
			<ymin>415</ymin>
			<xmax>421</xmax>
			<ymax>483</ymax>
		</bndbox>
	</object>
	<object>
		<name>ball</name>
		<pose>Unspecified</pose>
		<truncated>0</truncated>
		<difficult>0</difficult>
		<bndbox>
			<xmin>534</xmin>
			<ymin>475</ymin>
			<xmax>648</xmax>
			<ymax>584</ymax>
		</bndbox>
	</object>
	<object>
		<name>ball</name>
		<pose>Unspecified</pose>
		<truncated>0</truncated>
		<difficult>0</difficult>
		<bndbox>
			<xmin>812</xmin>
			<ymin>464</ymin>
			<xmax>936</xmax>
			<ymax>588</ymax>
		</bndbox>
	</object>
</annotation>
